companion/__init__.py
companion/error.py
companion/api/__init__.py
companion/api/backup.py
companion/api/deletebulk.py
companion/api/health.py
companion/api/reindex.py
companion/api/setup.py
companion/api/util.py
companion/cli/__init__.py
companion/cli/backup.py
companion/cli/cli.py
companion/cli/deletebulk.py
companion/cli/health.py
companion/cli/reindex.py
companion/cli/setup.py
elastic_companion-5.1.0.dist-info/DESCRIPTION.rst
elastic_companion-5.1.0.dist-info/METADATA
elastic_companion-5.1.0.dist-info/RECORD
elastic_companion-5.1.0.dist-info/WHEEL
elastic_companion-5.1.0.dist-info/entry_points.txt
elastic_companion-5.1.0.dist-info/metadata.json
elastic_companion-5.1.0.dist-info/top_level.txt
