Metadata-Version: 2.0
Name: elastic-companion
Version: 5.1.0
Summary: Useful commands for Elasticsearch
Home-page: https://github.com/getconversio/elastic-companion
Author: Conversio
Author-email: dev@conversio.com
License: MIT
Keywords: elasticsearch cli
Platform: UNKNOWN
Classifier: Development Status :: 5 - Production/Stable
Classifier: Intended Audience :: Developers
Classifier: Intended Audience :: System Administrators
Classifier: License :: OSI Approved :: MIT License
Classifier: Programming Language :: Python :: 3
Requires-Dist: boto3 (==1.4.0)
Requires-Dist: certifi (>=2016.8.31)
Requires-Dist: elasticsearch (>=5.0.0,<6.0.0)
Requires-Dist: python-dateutil (==2.5.3)
Provides-Extra: dev
Requires-Dist: coverage; extra == 'dev'
Requires-Dist: nose; extra == 'dev'
Requires-Dist: twine; extra == 'dev'
Requires-Dist: wheel; extra == 'dev'
